hankl/__init__.py
hankl/cosmology.py
hankl/fftlog.py
hankl/preprocess.py
hankl-1.1.0.dist-info/LICENSE
hankl-1.1.0.dist-info/METADATA
hankl-1.1.0.dist-info/WHEEL
hankl-1.1.0.dist-info/top_level.txt
hankl-1.1.0.dist-info/RECORD
