Metadata-Version: 2.1
Name: hankl
Version: 1.1.0
Summary: Lightweight FFTLog for Cosmology
Home-page: https://github.com/minaskar/hankl
Author: Minas Karamanis
Author-email: minaskar@gmail.com
License: UNKNOWN
Platform: UNKNOWN
Classifier: Programming Language :: Python :: 3
Classifier: License :: OSI Approved :: GNU General Public License v3 (GPLv3)
Classifier: Operating System :: OS Independent
Classifier: Intended Audience :: Science/Research
Classifier: Topic :: Scientific/Engineering
Classifier: Topic :: Scientific/Engineering :: Mathematics
Requires-Python: >=3.6
Requires-Dist: numpy
Requires-Dist: scipy
